moldrug/CustomMolDrugFitness.py
moldrug/CustomMoldrugFitness.py
moldrug/__init__.py
moldrug/_version.py
moldrug/cli.py
moldrug/constraintconf.py
moldrug/fitness.py
moldrug/home.py
moldrug/utils.py
moldrug/data/__init__.py
moldrug/data/_get.py
moldrug/data/6lu7/box.yml
moldrug/data/6lu7/ligand.smi
moldrug/data/6lu7/ligand_3D.mol
moldrug/data/6lu7/protein.pdb
moldrug/data/6lu7/protein.pdbqt
moldrug/data/x0161/box.yml
moldrug/data/x0161/ligand.smi
moldrug/data/x0161/ligand_3D.mol
moldrug/data/x0161/protein.pdb
moldrug/data/x0161/protein.pdbqt
moldrug-3.7.3.dist-info/LICENSE
moldrug-3.7.3.dist-info/METADATA
moldrug-3.7.3.dist-info/WHEEL
moldrug-3.7.3.dist-info/entry_points.txt
moldrug-3.7.3.dist-info/top_level.txt
moldrug-3.7.3.dist-info/RECORD
