Metadata-Version: 2.1
Name: moldrug
Version: 3.7.3
Summary: moldrug is a python package for drug-oriented optimization on the chemical space.
Author-email: Alejandro Martínez-León <ale94mleon@gmail.com>
License: Apache License
Project-URL: Hompage, https://github.com/ale94mleon/moldrug
Project-URL: Documentation, https://moldrug.readthedocs.io/en/latest/
Project-URL: Discussions, https://github.com/ale94mleon/moldrug/discussions
Project-URL: Issues, https://github.com/ale94mleon/moldrug/issues
Project-URL: Changelog, https://github.com/ale94mleon/moldrug/blob/main/docs/source/CHANGELOG.md
Keywords: science,chemistry,biology,drug-design,chemoinformatics,genetic algorithm
Classifier: Development Status :: 4 - Beta
Classifier: Operating System :: OS Independent
Classifier: Intended Audience :: Science/Research
Classifier: License :: OSI Approved :: Apache Software License
Classifier: Programming Language :: Python :: 3
Classifier: Programming Language :: Python :: 3.8
Classifier: Programming Language :: Python :: 3.9
Classifier: Programming Language :: Python :: 3.10
Classifier: Programming Language :: Python :: 3.11
Classifier: Topic :: Scientific/Engineering :: Bio-Informatics
Classifier: Topic :: Scientific/Engineering :: Chemistry
Requires-Python: <3.12,>=3.8
License-File: LICENSE
Requires-Dist: crem
Requires-Dist: tqdm
Requires-Dist: numpy
Requires-Dist: pandas
Requires-Dist: pyyaml
Requires-Dist: dill
Requires-Dist: meeko >=0.4.0
Requires-Dist: six
Requires-Dist: rdkit >=2022.3.5
Requires-Dist: scipy
Provides-Extra: dev
Requires-Dist: requests ; extra == 'dev'
Requires-Dist: pytest ; extra == 'dev'
